fast_sweep_ext.cpython-39-darwin.so
voronoi_ext.cpython-39-darwin.so
beat/__init__.py
beat/backend.py
beat/colormap.py
beat/config.py
beat/covariance.py
beat/defaults.py
beat/heart.py
beat/info.py
beat/inputf.py
beat/parallel.py
beat/pytensorf.py
beat/sources.py
beat/upgrade.py
beat/utility.py
beat/apps/__init__.py
beat/apps/beat.py
beat/apps/beatdown.py
beat/fast_sweeping/__init__.py
beat/fast_sweeping/fast_sweep.py
beat/fast_sweeping/fast_sweep_ext.c
beat/ffi/__init__.py
beat/ffi/base.py
beat/ffi/fault.py
beat/models/__init__.py
beat/models/base.py
beat/models/corrections.py
beat/models/distributions.py
beat/models/geodetic.py
beat/models/laplacian.py
beat/models/polarity.py
beat/models/problems.py
beat/models/seismic.py
beat/plotting/__init__.py
beat/plotting/bem.py
beat/plotting/common.py
beat/plotting/ffi.py
beat/plotting/geodetic.py
beat/plotting/marginals.py
beat/plotting/seismic.py
beat/sampler/__init__.py
beat/sampler/base.py
beat/sampler/distributed.py
beat/sampler/metropolis.py
beat/sampler/pt.py
beat/sampler/smc.py
beat/voronoi/__init__.py
beat/voronoi/voronoi.py
beat/voronoi/voronoi_ext.c
beat-2.0.2.dist-info/AUTHORS.md
beat-2.0.2.dist-info/METADATA
beat-2.0.2.dist-info/WHEEL
beat-2.0.2.dist-info/entry_points.txt
beat-2.0.2.dist-info/top_level.txt
beat-2.0.2.dist-info/RECORD
