Metadata-Version: 2.1
Name: beat
Version: 2.0.2
Summary: 'Bayesian Earthquake Analysis Tool'
Author-email: Hannes Vasyura-Bathke <vasbath@gfz-potsdam.de>
Maintainer-email: Hannes Vasyura-Bathke <vasbath@gfz-potsdam.de>
License: GPLv3
Project-URL: Home, https://pyrocko.org/beat
Project-URL: GitHub, https://github.com/hvasbath/beat
Project-URL: Issues, https://github.com/hvasbath/beat/issues
Keywords: Bayesian Inference,seismology,geodesy,earthquake,volcano
Classifier: Intended Audience :: Science/Research
Classifier: Topic :: Scientific/Engineering :: Physics
Classifier: Programming Language :: Python :: 3.9
Classifier: Programming Language :: C
Classifier: Operating System :: POSIX
Classifier: Operating System :: MacOS
Requires-Python: >=3.9
License-File: AUTHORS.md
Requires-Dist: numpy
Requires-Dist: scipy
Requires-Dist: pytensor>=2.18.4
Requires-Dist: pymc>=5.10.0
Requires-Dist: tqdm>=4.64.0
Requires-Dist: matplotlib>=3.1.1
Requires-Dist: psutil>=5.9.0
Requires-Dist: pyrocko>=2023.10.11
Provides-Extra: formatting
Requires-Dist: flake8; extra == "formatting"
Requires-Dist: ruff; extra == "formatting"
